stred/__init__.py
stred/cli.py
stred-0.1.0.dist-info/METADATA
stred-0.1.0.dist-info/WHEEL
stred-0.1.0.dist-info/entry_points.txt
stred-0.1.0.dist-info/top_level.txt
stred-0.1.0.dist-info/RECORD
