Metadata-Version: 2.4
Name: stred
Version: 0.1.0
Summary: STReam EDitor
Requires-Python: >=3.12
Requires-Dist: click>=8.3.1
Requires-Dist: jinja2>=3.1.6
